runagent/__init__.py
runagent/__version__.py
runagent/constants.py
runagent/cli/__init__.py
runagent/cli/branding.py
runagent/cli/main.py
runagent/cli/utils.py
runagent/cli/auth/__init__.py
runagent/cli/auth/device_client.py
runagent/cli/auth/device_flow.py
runagent/cli/commands/config.py
runagent/cli/commands/db.py
runagent/cli/commands/delete.py
runagent/cli/commands/deploy.py
runagent/cli/commands/init.py
runagent/cli/commands/register.py
runagent/cli/commands/run.py
runagent/cli/commands/run_stream.py
runagent/cli/commands/serve.py
runagent/cli/commands/setup.py
runagent/cli/commands/start.py
runagent/cli/commands/teardown.py
runagent/cli/commands/upload.py
runagent/cli/commands/whoami.py
runagent/client/__init__.py
runagent/client/client.py
runagent/sdk/__init__.py
runagent/sdk/config.py
runagent/sdk/db.py
runagent/sdk/exceptions.py
runagent/sdk/rest_client.py
runagent/sdk/sdk.py
runagent/sdk/socket_client.py
runagent/sdk/template_downloader.py
runagent/sdk/template_manager.py
runagent/sdk/deployment/__init__.py
runagent/sdk/deployment/middleware_sync.py
runagent/sdk/deployment/remote.py
runagent/sdk/server/__init__.py
runagent/sdk/server/local_server.py
runagent/sdk/server/socket_utils.py
runagent/sdk/server/framework/__init__.py
runagent/sdk/server/framework/ag2.py
runagent/sdk/server/framework/agno.py
runagent/sdk/server/framework/autogen.py
runagent/sdk/server/framework/crewai.py
runagent/sdk/server/framework/generic.py
runagent/sdk/server/framework/langchain.py
runagent/sdk/server/framework/langgraph.py
runagent/sdk/server/framework/letta.py
runagent/sdk/server/framework/llamaindex.py
runagent/sdk/server/framework/n8n.py
runagent/sdk/server/framework/openai.py
runagent/sdk/server/framework/parlant.py
runagent/utils/agent.py
runagent/utils/agent_id.py
runagent/utils/animation.py
runagent/utils/config.py
runagent/utils/env_vars.py
runagent/utils/gitignore.py
runagent/utils/imports.py
runagent/utils/logging_utils.py
runagent/utils/logs.py
runagent-0.1.47.dist-info/METADATA
runagent-0.1.47.dist-info/WHEEL
runagent-0.1.47.dist-info/entry_points.txt
runagent-0.1.47.dist-info/licenses/LICENSE
runagent-0.1.47.dist-info/RECORD
