Metadata-Version: 2.4
Name: runagent
Version: 0.1.47
Summary: A command-line tool and SDK for deploying, managing, and interacting with AI agents
Project-URL: Homepage, https://github.com/runagent-dev/runagent
Project-URL: Documentation, https://docs.runagent.live
Project-URL: Repository, https://github.com/runagent-dev/runagent.git
Project-URL: Issues, https://github.com/runagent-dev/runagent/issues
Project-URL: Discord, https://discord.gg/runagent
Project-URL: Changelog, https://github.com/runagent-dev/runagent/blob/main/CHANGELOG.md
Project-URL: Funding, https://github.com/sponsors/runagent-dev
Author-email: Sawradip Saha <sawradip0@gmail.com>
License-Expression: MIT
License-File: LICENSE
Keywords: agents,ai,automation,cli,langchain,langgraph,llm,sdk
Classifier: Development Status :: 4 - Beta
Classifier: Intended Audience :: Developers
Classifier: License :: OSI Approved :: MIT License
Classifier: Programming Language :: Python :: 3
Classifier: Programming Language :: Python :: 3.9
Classifier: Programming Language :: Python :: 3.10
Classifier: Programming Language :: Python :: 3.11
Classifier: Programming Language :: Python :: 3.12
Classifier: Topic :: Scientific/Engineering :: Artificial Intelligence
Classifier: Topic :: Software Development :: Libraries :: Application Frameworks
Classifier: Topic :: Software Development :: Libraries :: Python Modules
Classifier: Topic :: System :: Systems Administration
Classifier: Topic :: Utilities
Classifier: Typing :: Typed
Requires-Python: >=3.9
Requires-Dist: click>=8.1.7
Requires-Dist: fastapi==0.115.12
Requires-Dist: gitpython>=3.1.43
Requires-Dist: httpx==0.28.1
Requires-Dist: inquirer>=3.4.0
Requires-Dist: jsonpath-ng==1.7.0
Requires-Dist: pydantic>=2.6.1
Requires-Dist: python-dotenv>=1.0.0
Requires-Dist: pyyaml>=6.0.1
Requires-Dist: requests>=2.31.0
Requires-Dist: rich>=13.7.0
Requires-Dist: sqlalchemy==2.0.41
Requires-Dist: typing-extensions>=4.9.0
Requires-Dist: uvicorn==0.34.1
Requires-Dist: websockets==15.0.1
Provides-Extra: dev
Requires-Dist: bandit>=1.7.7; extra == 'dev'
Requires-Dist: black>=24.1.1; extra == 'dev'
Requires-Dist: coverage>=7.4.1; extra == 'dev'
Requires-Dist: flake8-docstrings>=1.7.0; extra == 'dev'
Requires-Dist: flake8>=7.0.0; extra == 'dev'
Requires-Dist: isort>=5.13.2; extra == 'dev'
Requires-Dist: mypy>=1.8.0; extra == 'dev'
Requires-Dist: pytest-asyncio>=0.23.5; extra == 'dev'
Requires-Dist: pytest-benchmark>=4.0.0; extra == 'dev'
Requires-Dist: pytest-cov>=4.1.0; extra == 'dev'
Requires-Dist: pytest-env>=1.1.3; extra == 'dev'
Requires-Dist: pytest-mock>=3.12.0; extra == 'dev'
Requires-Dist: pytest-sugar>=1.0.0; extra == 'dev'
Requires-Dist: pytest-xdist>=3.5.0; extra == 'dev'
Requires-Dist: pytest>=8.0.0; extra == 'dev'
Requires-Dist: safety>=2.3.5; extra == 'dev'
Requires-Dist: sphinx-autodoc-typehints>=2.0.1; extra == 'dev'
Requires-Dist: sphinx-rtd-theme>=2.0.0; extra == 'dev'
Requires-Dist: sphinx>=7.2.6; extra == 'dev'
